{"body":[{"text":"I died to these bosses 200 times during playtesting... https://t.co/Y9WaKThOdp","username":"DeadUnicornInc","tweet_url":"https://twitter.com/DeadUnicornInc/status/1863955010595573992","first_link":"https://x.com/DeadUnicornInc/status/1863955010595573992/video/1","created_at":"December 03, 2024 at 02:34PM","liked_at":"2024-12-05T00:26:15.684926","source":"ifttt","tweet_id":"1863955010595573992"},{"text":"#pixelart #IndieGameDev #Vampire\nBlood slashs🩸 https://t.co/06nsiWOqrw","username":"otsoga_","tweet_url":"https://twitter.com/otsoga_/status/1864383336820396275","first_link":"https://x.com/otsoga_/status/1864383336820396275/photo/1","created_at":"December 04, 2024 at 06:56PM","liked_at":"2024-12-05T00:21:15.605491","source":"ifttt","tweet_id":"1864383336820396275"}]}